{"list_name": "ETFs", "file_name": "etfs.json", "stock_list": {"4215217": {"symbol": "XLE", "long_name": "ENERGY SELECT SECTOR SPDR", "exchange": "ARCA"}, "4215205": {"symbol": "XLV", "long_name": "HEALTH CARE SELECT SECTOR", "exchange": "ARCA"}, "4215220": {"symbol": "XLF", "long_name": "FINANCIAL SELECT SECTOR SPDR", "exchange": "ARCA"}, "172522641": {"symbol": "ARKG", "long_name": "ARK GENOMIC REVOLUTION ETF", "exchange": "BATS"}, "172522644": {"symbol": "ARKK", "long_name": "ARK INNOVATION ETF", "exchange": "ARCA"}, "352320856": {"symbol": "ARKF", "long_name": "ARK FINTECH INNOVATION ETF", "exchange": "ARCA"}, "45540828": {"symbol": "XBI", "long_name": "SPDR S&P BIOTECH ETF", "exchange": "ARCA"}, "11517520": {"symbol": "IBB", "long_name": "ISHARES BIOTECHNOLOGY ETF", "exchange": "NASDAQ"}, "229725622": {"symbol": "SMH", "long_name": "VANECK SEMICONDUCTOR ETF", "exchange": "NASDAQ"}, "320227571": {"symbol": "QQQ", "long_name": "INVESCO QQQ TRUST SERIES 1", "exchange": "NASDAQ"}, "756733": {"symbol": "SPY", "long_name": "SPDR S&P 500 ETF TRUST", "exchange": "ARCA"}, "45540784": {"symbol": "XRT", "long_name": "SPDR S&P RETAIL ETF", "exchange": "ARCA"}, "4215215": {"symbol": "XLY", "long_name": "CONSUMER DISCRETIONARY SELT", "exchange": "ARCA"}}}